compdevkit/__init__.py
compdevkit/cli.py
compdevkit/exceptions.py
compdevkit/tests/__init__.py
compdevkit/tests/test_FunctionsTest.py
compdevkit-1.6.1.dist-info/LICENSE
compdevkit-1.6.1.dist-info/METADATA
compdevkit-1.6.1.dist-info/WHEEL
compdevkit-1.6.1.dist-info/entry_points.txt
compdevkit-1.6.1.dist-info/top_level.txt
compdevkit-1.6.1.dist-info/RECORD
