Metadata-Version: 2.1
Name: compdevkit
Version: 1.6.1
Summary: Developer tools for compmodels.org.
Home-page: https://github.com/comp-org/COMP-Developer-Toolkit
Author: Hank Doupe
Author-email: henrymdoupe@gmail.com
License: UNKNOWN
Platform: UNKNOWN
Classifier: Programming Language :: Python :: 3
Classifier: License :: OSI Approved :: MIT License
Classifier: Operating System :: OS Independent
Requires-Dist: paramtools (>=0.7.0)
Requires-Dist: boto3
Requires-Dist: s3like (>=1.3.1)
Requires-Dist: requests
